pydantic_config_generator/__init__.py
pydantic_config_generator/pydantic_config_generator.py
pydantic_config_generator-0.7.0.dist-info/licenses/LICENSE
pydantic_config_generator-0.7.0.dist-info/METADATA
pydantic_config_generator-0.7.0.dist-info/WHEEL
pydantic_config_generator-0.7.0.dist-info/top_level.txt
pydantic_config_generator-0.7.0.dist-info/RECORD
