Metadata-Version: 2.4
Name: pydantic-config-generator
Version: 0.7.0
Summary: Interactive configuration prompt for Pydantic models
Author-email: Dom <dom1984@gmail.com>
License: MIT
Project-URL: Homepage, https://github.com/dommolo/pydantic-config-generator
Project-URL: Repository, https://github.com/dommolo/pydantic-config-generator
Classifier: Development Status :: 3 - Alpha
Classifier: Intended Audience :: Developers
Classifier: Programming Language :: Python :: 3
Classifier: Programming Language :: Python :: 3.7
Classifier: Programming Language :: Python :: 3.8
Classifier: Programming Language :: Python :: 3.9
Classifier: Programming Language :: Python :: 3.10
Classifier: Programming Language :: Python :: 3.11
Requires-Python: >=3.7
License-File: LICENSE
Requires-Dist: pydantic<2.0,>=1.0
Dynamic: license-file
